mypkggener/__init__.py
mypkggener/core.py
mypkggener-0.0.1.dist-info/LICENSE
mypkggener-0.0.1.dist-info/METADATA
mypkggener-0.0.1.dist-info/WHEEL
mypkggener-0.0.1.dist-info/top_level.txt
mypkggener-0.0.1.dist-info/RECORD
