Metadata-Version: 2.1
Name: mypkggener
Version: 0.0.1
Summary: MyPyPIPkgDirGener
Home-page: https://github.com/FarAway6834/MyPkgGener
Author: FarAway6834
Author-email: faway6834@gmail.com
Keywords: FarAway,FarAway6834,MyPkgGener,PythonPkg2WheelableOnlinePkg,pypi
Classifier: Programming Language :: Python :: 3.10
Classifier: Programming Language :: Python :: 3.11
Classifier: Programming Language :: Python :: 3.12
Requires-Python: >=3.10
License-File: LICENSE
Requires-Dist: setuptools
Requires-Dist: wheel
Requires-Dist: twine
